[
{
  "directory": "/home/topisani/.bin/wm/src",
  "command": "/usr/bin/clang++    -g   -std=c++1z -o CMakeFiles/chwso.dir/chwso.cpp.o -c /home/topisani/.bin/wm/src/chwso.cpp",
  "file": "/home/topisani/.bin/wm/src/chwso.cpp"
},
{
  "directory": "/home/topisani/.bin/wm/src",
  "command": "/usr/bin/clang++    -g   -std=c++1z -o CMakeFiles/chwso.dir/util.cpp.o -c /home/topisani/.bin/wm/src/util.cpp",
  "file": "/home/topisani/.bin/wm/src/util.cpp"
},
{
  "directory": "/home/topisani/.bin/wm/src",
  "command": "/usr/bin/clang++    -g   -std=c++1z -o CMakeFiles/type.dir/type.cpp.o -c /home/topisani/.bin/wm/src/type.cpp",
  "file": "/home/topisani/.bin/wm/src/type.cpp"
},
{
  "directory": "/home/topisani/.bin/wm/src",
  "command": "/usr/bin/clang++    -g   -std=c++1z -o CMakeFiles/type.dir/util.cpp.o -c /home/topisani/.bin/wm/src/util.cpp",
  "file": "/home/topisani/.bin/wm/src/util.cpp"
},
{
  "directory": "/home/topisani/.bin/wm/src",
  "command": "/usr/bin/clang++    -g   -std=c++1z -o CMakeFiles/wname.dir/util.cpp.o -c /home/topisani/.bin/wm/src/util.cpp",
  "file": "/home/topisani/.bin/wm/src/util.cpp"
},
{
  "directory": "/home/topisani/.bin/wm/src",
  "command": "/usr/bin/clang++    -g   -std=c++1z -o CMakeFiles/wname.dir/wname.cpp.o -c /home/topisani/.bin/wm/src/wname.cpp",
  "file": "/home/topisani/.bin/wm/src/wname.cpp"
},
{
  "directory": "/home/topisani/.bin/wm/src",
  "command": "/usr/bin/clang++    -g   -std=c++1z -o CMakeFiles/tinywm.dir/tinywm.cpp.o -c /home/topisani/.bin/wm/src/tinywm.cpp",
  "file": "/home/topisani/.bin/wm/src/tinywm.cpp"
}
]